carpoolsim/__init__.py
carpoolsim/basic_settings.py
carpoolsim/carpool/__init__.py
carpoolsim/carpool/sim.py
carpoolsim/carpool/trip_cluster_abstract.py
carpoolsim/carpool/trip_cluster_dc.py
carpoolsim/carpool/trip_cluster_pnr.py
carpoolsim/carpool/trip_demands.py
carpoolsim/carpool/util/evaluator.py
carpoolsim/carpool/util/filters_dc.py
carpoolsim/carpool/util/filters_pnr.py
carpoolsim/carpool/util/io.py
carpoolsim/carpool/util/mat_operations.py
carpoolsim/carpool/util/network_search.py
carpoolsim/carpool/util/plotter.py
carpoolsim/carpool/util/solver.py
carpoolsim/carpool_solver/__init__.py
carpoolsim/carpool_solver/bipartite_solver.py
carpoolsim/config.py
carpoolsim/database/__init__.py
carpoolsim/database/prepare_database.py
carpoolsim/database/query_database.py
carpoolsim/dataclass/__init__.py
carpoolsim/dataclass/parking_lots.py
carpoolsim/dataclass/traffic_network.py
carpoolsim/dataclass/travel_demands.py
carpoolsim/dataclass/utils.py
carpoolsim/network_prepare.py
carpoolsim/prepare_input.py
carpoolsim/visualization/__init__.py
carpoolsim/visualization/carpool_viz.py
carpoolsim/visualization/carpool_viz_seq.py
carpoolsim-0.2.0.dist-info/METADATA
carpoolsim-0.2.0.dist-info/WHEEL
carpoolsim-0.2.0.dist-info/RECORD
