Metadata-Version: 2.3
Name: carpoolsim
Version: 0.2.0
Summary: A simulation tool to find as many as carpool-able trips given drive-alone trips
License: GPL-3.0-or-later
Author: Diyi Liu
Requires-Python: >=3.11,<4.0
Classifier: License :: OSI Approved :: GNU General Public License v3 or later (GPLv3+)
Classifier: Programming Language :: Python :: 3
Classifier: Programming Language :: Python :: 3.11
Classifier: Programming Language :: Python :: 3.12
Classifier: Programming Language :: Python :: 3.13
Requires-Dist: contextily (>=1.6.0,<2.0.0)
Requires-Dist: geopandas (>=0.14.3,<0.15.0)
Requires-Dist: gurobipy (>=11.0.1,<12.0.0)
Requires-Dist: jupyterlab (>=4.1.5,<5.0.0)
Requires-Dist: matplotlib (>=3.8.3,<4.0.0)
Requires-Dist: multiprocess (>=0.70.16,<0.71.0)
Requires-Dist: networkx (>=3.2.1,<4.0.0)
Requires-Dist: numpy (>=1.26.4,<2.0.0)
Requires-Dist: pandas (>=2.2.1,<3.0.0)
Requires-Dist: shapely (>=2.0.3,<3.0.0)
Requires-Dist: sqlalchemy (>=2.0.29,<3.0.0)
